torch_graphgen/__init__.py
torch_graphgen/graphgen.py
torch_graphgen/utils/__init__.py
torch_graphgen/utils/graph.py
torch_graphgen/utils/inclusion.py
torch_graphgen/utils/stats.py
torch_graphgen-1.0.4.dist-info/LICENSE
torch_graphgen-1.0.4.dist-info/METADATA
torch_graphgen-1.0.4.dist-info/WHEEL
torch_graphgen-1.0.4.dist-info/RECORD
