Metadata-Version: 2.1
Name: torch-graphgen
Version: 1.0.4
Summary: Generate graph representations of deep neural networks compatible with torch-geometric
License: GPL-3.0-only
Author: Quoding
Author-email: quoding@protonmail.ch
Requires-Python: >=3.8,<4.0
Classifier: License :: OSI Approved :: GNU General Public License v3 (GPLv3)
Classifier: Programming Language :: Python :: 3
Classifier: Programming Language :: Python :: 3.8
Classifier: Programming Language :: Python :: 3.9
Classifier: Programming Language :: Python :: 3.10
Classifier: Programming Language :: Python :: 3.11
Classifier: Programming Language :: Python :: 3.12
